Workbook

Sheet Resumo
A1: RESUMO FINANCEIRO - Visão Geral
A3: Mês de referência: | B3: Janeiro
A5: Total de Receitas (mês) | B5: =SUMIFS(Transações!$F$4:$F$400,Transações!$D$4:$D$400,"Receita",Transações!$H$4:$H$400,$B$3) -> 6500
A6: Total de Despesas (mês) | B6: =SUMIFS(Transações!$F$4:$F$400,Transações!$D$4:$D$400,"Despesa",Transações!$H$4:$H$400,$B$3) -> 2870.3
A7: Saldo do Mês | B7: =B5-B6 -> 3629.7
A8: Saldo Acumulado (total) | B8: =SUMIFS(Transações!$F$4:$F$400,Transações!$D$4:$D$400,"Receita")-SUMIFS(Transações!$F$4:$F$400,Transações!$D$4:$D$400,"Despesa") -> 3629.7
A10: Despesas por Categoria (mês selecionado) | D10: Receitas por Categoria (mês selecionado)
A11: Categoria | B11: Valor | D11: Categoria | E11: Valor
A12: Moradia (aluguel/condomínio) | B12: =SUMIFS(Transações!$F$4:$F$400,Transações!$D$4:$D$400,"Despesa",Transações!$C$4:$C$400,$A12,Transações!$H$4:$H$400,$B$3) -> 1800 | D12: Salário | E12: =SUMIFS(Transações!$F$4:$F$400,Transações!$D$4:$D$400,"Receita",Transações!$C$4:$C$400,$D12,Transações!$H$4:$H$400,$B$3) -> 6500
A13: Contas (água/luz/gás/internet) | B13: =SUMIFS(Transações!$F$4:$F$400,Transações!$D$4:$D$400,"Despesa",Transações!$C$4:$C$400,$A13,Transações!$H$4:$H$400,$B$3) -> 220 | D13: Freelance/Extra | E13: =SUMIFS(Transações!$F$4:$F$400,Transações!$D$4:$D$400,"Receita",Transações!$C$4:$C$400,$D13,Transações!$H$4:$H$400,$B$3) -> 0
A14: Alimentação/Mercado | B14: =SUMIFS(Transações!$F$4:$F$400,Transações!$D$4:$D$400,"Despesa",Transações!$C$4:$C$400,$A14,Transações!$H$4:$H$400,$B$3) -> 850.3 | D14: Rendimentos/Investimentos | E14: =SUMIFS(Transações!$F$4:$F$400,Transações!$D$4:$D$400,"Receita",Transações!$C$4:$C$400,$D14,Transações!$H$4:$H$400,$B$3) -> 0
A15: Transporte/Combustível | B15: =SUMIFS(Transações!$F$4:$F$400,Transações!$D$4:$D$400,"Despesa",Transações!$C$4:$C$400,$A15,Transações!$H$4:$H$400,$B$3) -> 0 | D15: Aluguel Recebido | E15: =SUMIFS(Transações!$F$4:$F$400,Transações!$D$4:$D$400,"Receita",Transações!$C$4:$C$400,$D15,Transações!$H$4:$H$400,$B$3) -> 0
A16: Saúde/Plano de Saúde | B16: =SUMIFS(Transações!$F$4:$F$400,Transações!$D$4:$D$400,"Despesa",Transações!$C$4:$C$400,$A16,Transações!$H$4:$H$400,$B$3) -> 0 | D16: Reembolso | E16: =SUMIFS(Transações!$F$4:$F$400,Transações!$D$4:$D$400,"Receita",Transações!$C$4:$C$400,$D16,Transações!$H$4:$H$400,$B$3) -> 0
A17: Educação | B17: =SUMIFS(Transações!$F$4:$F$400,Transações!$D$4:$D$400,"Despesa",Transações!$C$4:$C$400,$A17,Transações!$H$4:$H$400,$B$3) -> 0 | D17: Décimo Terceiro/Férias | E17: =SUMIFS(Transações!$F$4:$F$400,Transações!$D$4:$D$400,"Receita",Transações!$C$4:$C$400,$D17,Transações!$H$4:$H$400,$B$3) -> 0
A18: Lazer/Assinaturas | B18: =SUMIFS(Transações!$F$4:$F$400,Transações!$D$4:$D$400,"Despesa",Transações!$C$4:$C$400,$A18,Transações!$H$4:$H$400,$B$3) -> 0 | D18: Outras Receitas | E18: =SUMIFS(Transações!$F$4:$F$400,Transações!$D$4:$D$400,"Receita",Transações!$C$4:$C$400,$D18,Transações!$H$4:$H$400,$B$3) -> 0
A19: Vestuário | B19: =SUMIFS(Transações!$F$4:$F$400,Transações!$D$4:$D$400,"Despesa",Transações!$C$4:$C$400,$A19,Transações!$H$4:$H$400,$B$3) -> 0 | D19: Total | E19: =SUM(E12:E18) -> 6500
A20: Cuidados Pessoais | B20: =SUMIFS(Transações!$F$4:$F$400,Transações!$D$4:$D$400,"Despesa",Transações!$C$4:$C$400,$A20,Transações!$H$4:$H$400,$B$3) -> 0
A21: Cartão de Crédito | B21: =SUMIFS(Transações!$F$4:$F$400,Transações!$D$4:$D$400,"Despesa",Transações!$C$4:$C$400,$A21,Transações!$H$4:$H$400,$B$3) -> 0
A22: Dívidas/Empréstimos | B22: =SUMIFS(Transações!$F$4:$F$400,Transações!$D$4:$D$400,"Despesa",Transações!$C$4:$C$400,$A22,Transações!$H$4:$H$400,$B$3) -> 0
A23: Impostos/Taxas | B23: =SUMIFS(Transações!$F$4:$F$400,Transações!$D$4:$D$400,"Despesa",Transações!$C$4:$C$400,$A23,Transações!$H$4:$H$400,$B$3) -> 0
A24: Doações | B24: =SUMIFS(Transações!$F$4:$F$400,Transações!$D$4:$D$400,"Despesa",Transações!$C$4:$C$400,$A24,Transações!$H$4:$H$400,$B$3) -> 0
A25: Pets | B25: =SUMIFS(Transações!$F$4:$F$400,Transações!$D$4:$D$400,"Despesa",Transações!$C$4:$C$400,$A25,Transações!$H$4:$H$400,$B$3) -> 0
A26: Investimentos/Poupança | B26: =SUMIFS(Transações!$F$4:$F$400,Transações!$D$4:$D$400,"Despesa",Transações!$C$4:$C$400,$A26,Transações!$H$4:$H$400,$B$3) -> 0
A27: Outras Despesas | B27: =SUMIFS(Transações!$F$4:$F$400,Transações!$D$4:$D$400,"Despesa",Transações!$C$4:$C$400,$A27,Transações!$H$4:$H$400,$B$3) -> 0
A28: Total | B28: =SUM(B12:B27) -> 2870.3

Sheet Transações
A1: TRANSAÇÕES - Lançamentos de Receitas e Despesas
A2: Legenda: preencha as colunas A a E, G e J (fundo amarelo = campo de entrada). As colunas Mês e Ano são calculadas automaticamente a partir da Data.
A3: Data | B3: Descrição | C3: Categoria | D3: Tipo | E3: Forma de Pagamento | F3: Valor | G3: Status | H3: Mês | I3: Ano | J3: Observações
A4: 46027 | B4: Salário mensal | C4: Salário | D4: Receita | E4: Transferência | F4: 6500 | G4: Pago | H4: =IF(A4="","",INDEX(Lista_Meses,MONTH(A4))) -> Janeiro | I4: =IF(A4="","",YEAR(A4)) -> 2026 | J4: Exemplo ilustrativo
A5: 46029 | B5: Supermercado do mês | C5: Alimentação/Mercado | D5: Despesa | E5: Débito | F5: 850.3 | G5: Pago | H5: =IF(A5="","",INDEX(Lista_Meses,MONTH(A5))) -> Janeiro | I5: =IF(A5="","",YEAR(A5)) -> 2026
A6: 46032 | B6: Aluguel | C6: Moradia (aluguel/condomínio) | D6: Despesa | E6: Boleto | F6: 1800 | G6: Pago | H6: =IF(A6="","",INDEX(Lista_Meses,MONTH(A6))) -> Janeiro | I6: =IF(A6="","",YEAR(A6)) -> 2026
A7: 46037 | B7: Conta de luz | C7: Contas (água/luz/gás/internet) | D7: Despesa | E7: Pix | F7: 220 | G7: Pago | H7: =IF(A7="","",INDEX(Lista_Meses,MONTH(A7))) -> Janeiro | I7: =IF(A7="","",YEAR(A7)) -> 2026
H8: =IF(A8="","",INDEX(Lista_Meses,MONTH(A8))) | I8: =IF(A8="","",YEAR(A8))
H9: =IF(A9="","",INDEX(Lista_Meses,MONTH(A9))) | I9: =IF(A9="","",YEAR(A9))
H10: =IF(A10="","",INDEX(Lista_Meses,MONTH(A10))) | I10: =IF(A10="","",YEAR(A10))
H11: =IF(A11="","",INDEX(Lista_Meses,MONTH(A11))) | I11: =IF(A11="","",YEAR(A11))
H12: =IF(A12="","",INDEX(Lista_Meses,MONTH(A12))) | I12: =IF(A12="","",YEAR(A12))
H13: =IF(A13="","",INDEX(Lista_Meses,MONTH(A13))) | I13: =IF(A13="","",YEAR(A13))
H14: =IF(A14="","",INDEX(Lista_Meses,MONTH(A14))) | I14: =IF(A14="","",YEAR(A14))
H15: =IF(A15="","",INDEX(Lista_Meses,MONTH(A15))) | I15: =IF(A15="","",YEAR(A15))
H16: =IF(A16="","",INDEX(Lista_Meses,MONTH(A16))) | I16: =IF(A16="","",YEAR(A16))
H17: =IF(A17="","",INDEX(Lista_Meses,MONTH(A17))) | I17: =IF(A17="","",YEAR(A17))
H18: =IF(A18="","",INDEX(Lista_Meses,MONTH(A18))) | I18: =IF(A18="","",YEAR(A18))
H19: =IF(A19="","",INDEX(Lista_Meses,MONTH(A19))) | I19: =IF(A19="","",YEAR(A19))
... H400: =IF(A400="","",INDEX(Lista_Meses,MONTH(A400))) | I400: =IF(A400="","",YEAR(A400))

Sheet Orçamento Mensal
A1: ORÇAMENTO MENSAL - Planejado vs Realizado
A2: Legenda: preencha a coluna Orçado (fundo amarelo) com o valor planejado para cada categoria. Realizado é calculado automaticamente a partir da aba Transações.
A3: Mês de referência: | B3: Janeiro
A5: Categoria | B5: Orçado | C5: Realizado | D5: Diferença | E5: % Utilizado
A6: Moradia (aluguel/condomínio) | B6: 0 | C6: =SUMIFS(Transações!$F$4:$F$400,Transações!$D$4:$D$400,"Despesa",Transações!$C$4:$C$400,$A6,Transações!$H$4:$H$400,$B$3) -> 1800 | D6: =B6-C6 -> -1800 | E6: =IFERROR(C6/B6,"-") -> -
A7: Contas (água/luz/gás/internet) | B7: 0 | C7: =SUMIFS(Transações!$F$4:$F$400,Transações!$D$4:$D$400,"Despesa",Transações!$C$4:$C$400,$A7,Transações!$H$4:$H$400,$B$3) -> 220 | D7: =B7-C7 -> -220 | E7: =IFERROR(C7/B7,"-") -> -
A8: Alimentação/Mercado | B8: 0 | C8: =SUMIFS(Transações!$F$4:$F$400,Transações!$D$4:$D$400,"Despesa",Transações!$C$4:$C$400,$A8,Transações!$H$4:$H$400,$B$3) -> 850.3 | D8: =B8-C8 -> -850.3 | E8: =IFERROR(C8/B8,"-") -> -
A9: Transporte/Combustível | B9: 0 | C9: =SUMIFS(Transações!$F$4:$F$400,Transações!$D$4:$D$400,"Despesa",Transações!$C$4:$C$400,$A9,Transações!$H$4:$H$400,$B$3) -> 0 | D9: =B9-C9 -> 0 | E9: =IFERROR(C9/B9,"-") -> -
A10: Saúde/Plano de Saúde | B10: 0 | C10: =SUMIFS(Transações!$F$4:$F$400,Transações!$D$4:$D$400,"Despesa",Transações!$C$4:$C$400,$A10,Transações!$H$4:$H$400,$B$3) -> 0 | D10: =B10-C10 -> 0 | E10: =IFERROR(C10/B10,"-") -> -
A11: Educação | B11: 0 | C11: =SUMIFS(Transações!$F$4:$F$400,Transações!$D$4:$D$400,"Despesa",Transações!$C$4:$C$400,$A11,Transações!$H$4:$H$400,$B$3) -> 0 | D11: =B11-C11 -> 0 | E11: =IFERROR(C11/B11,"-") -> -
A12: Lazer/Assinaturas | B12: 0 | C12: =SUMIFS(Transações!$F$4:$F$400,Transações!$D$4:$D$400,"Despesa",Transações!$C$4:$C$400,$A12,Transações!$H$4:$H$400,$B$3) -> 0 | D12: =B12-C12 -> 0 | E12: =IFERROR(C12/B12,"-") -> -
A13: Vestuário | B13: 0 | C13: =SUMIFS(Transações!$F$4:$F$400,Transações!$D$4:$D$400,"Despesa",Transações!$C$4:$C$400,$A13,Transações!$H$4:$H$400,$B$3) -> 0 | D13: =B13-C13 -> 0 | E13: =IFERROR(C13/B13,"-") -> -
A14: Cuidados Pessoais | B14: 0 | C14: =SUMIFS(Transações!$F$4:$F$400,Transações!$D$4:$D$400,"Despesa",Transações!$C$4:$C$400,$A14,Transações!$H$4:$H$400,$B$3) -> 0 | D14: =B14-C14 -> 0 | E14: =IFERROR(C14/B14,"-") -> -
A15: Cartão de Crédito | B15: 0 | C15: =SUMIFS(Transações!$F$4:$F$400,Transações!$D$4:$D$400,"Despesa",Transações!$C$4:$C$400,$A15,Transações!$H$4:$H$400,$B$3) -> 0 | D15: =B15-C15 -> 0 | E15: =IFERROR(C15/B15,"-") -> -
A16: Dívidas/Empréstimos | B16: 0 | C16: =SUMIFS(Transações!$F$4:$F$400,Transações!$D$4:$D$400,"Despesa",Transações!$C$4:$C$400,$A16,Transações!$H$4:$H$400,$B$3) -> 0 | D16: =B16-C16 -> 0 | E16: =IFERROR(C16/B16,"-") -> -
A17: Impostos/Taxas | B17: 0 | C17: =SUMIFS(Transações!$F$4:$F$400,Transações!$D$4:$D$400,"Despesa",Transações!$C$4:$C$400,$A17,Transações!$H$4:$H$400,$B$3) -> 0 | D17: =B17-C17 -> 0 | E17: =IFERROR(C17/B17,"-") -> -
... A21: Outras Despesas | B21: 0 | C21: =SUMIFS(Transações!$F$4:$F$400,Transações!$D$4:$D$400,"Despesa",Transações!$C$4:$C$400,$A21,Transações!$H$4:$H$400,$B$3) -> 0 | D21: =B21-C21 -> 0 | E21: =IFERROR(C21/B21,"-") -> -
A22: Total | B22: =SUM(B6:B21) -> 0 | C22: =SUM(C6:C21) -> 2870.3 | D22: =SUM(D6:D21) -> -2870.3 | E22: =IFERROR(C22/B22,"-") -> -

Sheet Fluxo Anual
A1: FLUXO DE CAIXA ANUAL - Receitas x Despesas por Mês
A3: Ano de referência: | B3: 2026
A5: Item | B5: Janeiro | C5: Fevereiro | D5: Março | E5: Abril | F5: Maio | G5: Junho | H5: Julho | I5: Agosto | J5: Setembro | K5: Outubro | L5: Novembro | M5: Dezembro | N5: Total Ano
A6: Receitas Totais | B6: =SUMIFS(Transações!$F$4:$F$400,Transações!$D$4:$D$400,"Receita",Transações!$H$4:$H$400,B$5,Transações!$I$4:$I$400,$B$3) -> 6500 | C6: =SUMIFS(Transações!$F$4:$F$400,Transações!$D$4:$D$400,"Receita",Transações!$H$4:$H$400,C$5,Transações!$I$4:$I$400,$B$3) -> 0 | D6: =SUMIFS(Transações!$F$4:$F$400,Transações!$D$4:$D$400,"Receita",Transações!$H$4:$H$400,D$5,Transações!$I$4:$I$400,$B$3) -> 0 | E6: =SUMIFS(Transações!$F$4:$F$400,Transações!$D$4:$D$400,"Receita",Transações!$H$4:$H$400,E$5,Transações!$I$4:$I$400,$B$3) -> 0 | F6: =SUMIFS(Transações!$F$4:$F$400,Transações!$D$4:$D$400,"Receita",Transações!$H$4:$H$400,F$5,Transações!$I$4:$I$400,$B$3) -> 0 | G6: =SUMIFS(Transações!$F$4:$F$400,Transações!$D$4:$D$400,"Receita",Transações!$H$4:$H$400,G$5,Transações!$I$4:$I$400,$B$3) -> 0 | H6: =SUMIFS(Transações!$F$4:$F$400,Transações!$D$4:$D$400,"Receita",Transações!$H$4:$H$400,H$5,Transações!$I$4:$I$400,$B$3) -> 0 | I6: =SUMIFS(Transações!$F$4:$F$400,Transações!$D$4:$D$400,"Receita",Transações!$H$4:$H$400,I$5,Transações!$I$4:$I$400,$B$3) -> 0 | ... M6: =SUMIFS(Transações!$F$4:$F$400,Transações!$D$4:$D$400,"Receita",Transações!$H$4:$H$400,M$5,Transações!$I$4:$I$400,$B$3) -> 0 | N6: =SUM(B6:M6) -> 6500
A7: Moradia (aluguel/condomínio) | B7: =SUMIFS(Transações!$F$4:$F$400,Transações!$D$4:$D$400,"Despesa",Transações!$C$4:$C$400,$A7,Transações!$H$4:$H$400,B$5,Transações!$I$4:$I$400,$B$3) -> 1800 | C7: =SUMIFS(Transações!$F$4:$F$400,Transações!$D$4:$D$400,"Despesa",Transações!$C$4:$C$400,$A7,Transações!$H$4:$H$400,C$5,Transações!$I$4:$I$400,$B$3) -> 0 | D7: =SUMIFS(Transações!$F$4:$F$400,Transações!$D$4:$D$400,"Despesa",Transações!$C$4:$C$400,$A7,Transações!$H$4:$H$400,D$5,Transações!$I$4:$I$400,$B$3) -> 0 | E7: =SUMIFS(Transações!$F$4:$F$400,Transações!$D$4:$D$400,"Despesa",Transações!$C$4:$C$400,$A7,Transações!$H$4:$H$400,E$5,Transações!$I$4:$I$400,$B$3) -> 0 | F7: =SUMIFS(Transações!$F$4:$F$400,Transações!$D$4:$D$400,"Despesa",Transações!$C$4:$C$400,$A7,Transações!$H$4:$H$400,F$5,Transações!$I$4:$I$400,$B$3) -> 0 | G7: =SUMIFS(Transações!$F$4:$F$400,Transações!$D$4:$D$400,"Despesa",Transações!$C$4:$C$400,$A7,Transações!$H$4:$H$400,G$5,Transações!$I$4:$I$400,$B$3) -> 0 | H7: =SUMIFS(Transações!$F$4:$F$400,Transações!$D$4:$D$400,"Despesa",Transações!$C$4:$C$400,$A7,Transações!$H$4:$H$400,H$5,Transações!$I$4:$I$400,$B$3) -> 0 | I7: =SUMIFS(Transações!$F$4:$F$400,Transações!$D$4:$D$400,"Despesa",Transações!$C$4:$C$400,$A7,Transações!$H$4:$H$400,I$5,Transações!$I$4:$I$400,$B$3) -> 0 | ... M7: =SUMIFS(Transações!$F$4:$F$400,Transações!$D$4:$D$400,"Despesa",Transações!$C$4:$C$400,$A7,Transações!$H$4:$H$400,M$5,Transações!$I$4:$I$400,$B$3) -> 0 | N7: =SUM(B7:M7) -> 1800
A8: Contas (água/luz/gás/internet) | B8: =SUMIFS(Transações!$F$4:$F$400,Transações!$D$4:$D$400,"Despesa",Transações!$C$4:$C$400,$A8,Transações!$H$4:$H$400,B$5,Transações!$I$4:$I$400,$B$3) -> 220 | C8: =SUMIFS(Transações!$F$4:$F$400,Transações!$D$4:$D$400,"Despesa",Transações!$C$4:$C$400,$A8,Transações!$H$4:$H$400,C$5,Transações!$I$4:$I$400,$B$3) -> 0 | D8: =SUMIFS(Transações!$F$4:$F$400,Transações!$D$4:$D$400,"Despesa",Transações!$C$4:$C$400,$A8,Transações!$H$4:$H$400,D$5,Transações!$I$4:$I$400,$B$3) -> 0 | E8: =SUMIFS(Transações!$F$4:$F$400,Transações!$D$4:$D$400,"Despesa",Transações!$C$4:$C$400,$A8,Transações!$H$4:$H$400,E$5,Transações!$I$4:$I$400,$B$3) -> 0 | F8: =SUMIFS(Transações!$F$4:$F$400,Transações!$D$4:$D$400,"Despesa",Transações!$C$4:$C$400,$A8,Transações!$H$4:$H$400,F$5,Transações!$I$4:$I$400,$B$3) -> 0 | G8: =SUMIFS(Transações!$F$4:$F$400,Transações!$D$4:$D$400,"Despesa",Transações!$C$4:$C$400,$A8,Transações!$H$4:$H$400,G$5,Transações!$I$4:$I$400,$B$3) -> 0 | H8: =SUMIFS(Transações!$F$4:$F$400,Transações!$D$4:$D$400,"Despesa",Transações!$C$4:$C$400,$A8,Transações!$H$4:$H$400,H$5,Transações!$I$4:$I$400,$B$3) -> 0 | I8: =SUMIFS(Transações!$F$4:$F$400,Transações!$D$4:$D$400,"Despesa",Transações!$C$4:$C$400,$A8,Transações!$H$4:$H$400,I$5,Transações!$I$4:$I$400,$B$3) -> 0 | ... M8: =SUMIFS(Transações!$F$4:$F$400,Transações!$D$4:$D$400,"Despesa",Transações!$C$4:$C$400,$A8,Transações!$H$4:$H$400,M$5,Transações!$I$4:$I$400,$B$3) -> 0 | N8: =SUM(B8:M8) -> 220
A9: Alimentação/Mercado | B9: =SUMIFS(Transações!$F$4:$F$400,Transações!$D$4:$D$400,"Despesa",Transações!$C$4:$C$400,$A9,Transações!$H$4:$H$400,B$5,Transações!$I$4:$I$400,$B$3) -> 850.3 | C9: =SUMIFS(Transações!$F$4:$F$400,Transações!$D$4:$D$400,"Despesa",Transações!$C$4:$C$400,$A9,Transações!$H$4:$H$400,C$5,Transações!$I$4:$I$400,$B$3) -> 0 | D9: =SUMIFS(Transações!$F$4:$F$400,Transações!$D$4:$D$400,"Despesa",Transações!$C$4:$C$400,$A9,Transações!$H$4:$H$400,D$5,Transações!$I$4:$I$400,$B$3) -> 0 | E9: =SUMIFS(Transações!$F$4:$F$400,Transações!$D$4:$D$400,"Despesa",Transações!$C$4:$C$400,$A9,Transações!$H$4:$H$400,E$5,Transações!$I$4:$I$400,$B$3) -> 0 | F9: =SUMIFS(Transações!$F$4:$F$400,Transações!$D$4:$D$400,"Despesa",Transações!$C$4:$C$400,$A9,Transações!$H$4:$H$400,F$5,Transações!$I$4:$I$400,$B$3) -> 0 | G9: =SUMIFS(Transações!$F$4:$F$400,Transações!$D$4:$D$400,"Despesa",Transações!$C$4:$C$400,$A9,Transações!$H$4:$H$400,G$5,Transações!$I$4:$I$400,$B$3) -> 0 | H9: =SUMIFS(Transações!$F$4:$F$400,Transações!$D$4:$D$400,"Despesa",Transações!$C$4:$C$400,$A9,Transações!$H$4:$H$400,H$5,Transações!$I$4:$I$400,$B$3) -> 0 | I9: =SUMIFS(Transações!$F$4:$F$400,Transações!$D$4:$D$400,"Despesa",Transações!$C$4:$C$400,$A9,Transações!$H$4:$H$400,I$5,Transações!$I$4:$I$400,$B$3) -> 0 | ... M9: =SUMIFS(Transações!$F$4:$F$400,Transações!$D$4:$D$400,"Despesa",Transações!$C$4:$C$400,$A9,Transações!$H$4:$H$400,M$5,Transações!$I$4:$I$400,$B$3) -> 0 | N9: =SUM(B9:M9) -> 850.3
A10: Transporte/Combustível | B10: =SUMIFS(Transações!$F$4:$F$400,Transações!$D$4:$D$400,"Despesa",Transações!$C$4:$C$400,$A10,Transações!$H$4:$H$400,B$5,Transações!$I$4:$I$400,$B$3) -> 0 | C10: =SUMIFS(Transações!$F$4:$F$400,Transações!$D$4:$D$400,"Despesa",Transações!$C$4:$C$400,$A10,Transações!$H$4:$H$400,C$5,Transações!$I$4:$I$400,$B$3) -> 0 | D10: =SUMIFS(Transações!$F$4:$F$400,Transações!$D$4:$D$400,"Despesa",Transações!$C$4:$C$400,$A10,Transações!$H$4:$H$400,D$5,Transações!$I$4:$I$400,$B$3) -> 0 | E10: =SUMIFS(Transações!$F$4:$F$400,Transações!$D$4:$D$400,"Despesa",Transações!$C$4:$C$400,$A10,Transações!$H$4:$H$400,E$5,Transações!$I$4:$I$400,$B$3) -> 0 | F10: =SUMIFS(Transações!$F$4:$F$400,Transações!$D$4:$D$400,"Despesa",Transações!$C$4:$C$400,$A10,Transações!$H$4:$H$400,F$5,Transações!$I$4:$I$400,$B$3) -> 0 | G10: =SUMIFS(Transações!$F$4:$F$400,Transações!$D$4:$D$400,"Despesa",Transações!$C$4:$C$400,$A10,Transações!$H$4:$H$400,G$5,Transações!$I$4:$I$400,$B$3) -> 0 | H10: =SUMIFS(Transações!$F$4:$F$400,Transações!$D$4:$D$400,"Despesa",Transações!$C$4:$C$400,$A10,Transações!$H$4:$H$400,H$5,Transações!$I$4:$I$400,$B$3) -> 0 | I10: =SUMIFS(Transações!$F$4:$F$400,Transações!$D$4:$D$400,"Despesa",Transações!$C$4:$C$400,$A10,Transações!$H$4:$H$400,I$5,Transações!$I$4:$I$400,$B$3) -> 0 | ... M10: =SUMIFS(Transações!$F$4:$F$400,Transações!$D$4:$D$400,"Despesa",Transações!$C$4:$C$400,$A10,Transações!$H$4:$H$400,M$5,Transações!$I$4:$I$400,$B$3) -> 0 | N10: =SUM(B10:M10) -> 0
A11: Saúde/Plano de Saúde | B11: =SUMIFS(Transações!$F$4:$F$400,Transações!$D$4:$D$400,"Despesa",Transações!$C$4:$C$400,$A11,Transações!$H$4:$H$400,B$5,Transações!$I$4:$I$400,$B$3) -> 0 | C11: =SUMIFS(Transações!$F$4:$F$400,Transações!$D$4:$D$400,"Despesa",Transações!$C$4:$C$400,$A11,Transações!$H$4:$H$400,C$5,Transações!$I$4:$I$400,$B$3) -> 0 | D11: =SUMIFS(Transações!$F$4:$F$400,Transações!$D$4:$D$400,"Despesa",Transações!$C$4:$C$400,$A11,Transações!$H$4:$H$400,D$5,Transações!$I$4:$I$400,$B$3) -> 0 | E11: =SUMIFS(Transações!$F$4:$F$400,Transações!$D$4:$D$400,"Despesa",Transações!$C$4:$C$400,$A11,Transações!$H$4:$H$400,E$5,Transações!$I$4:$I$400,$B$3) -> 0 | F11: =SUMIFS(Transações!$F$4:$F$400,Transações!$D$4:$D$400,"Despesa",Transações!$C$4:$C$400,$A11,Transações!$H$4:$H$400,F$5,Transações!$I$4:$I$400,$B$3) -> 0 | G11: =SUMIFS(Transações!$F$4:$F$400,Transações!$D$4:$D$400,"Despesa",Transações!$C$4:$C$400,$A11,Transações!$H$4:$H$400,G$5,Transações!$I$4:$I$400,$B$3) -> 0 | H11: =SUMIFS(Transações!$F$4:$F$400,Transações!$D$4:$D$400,"Despesa",Transações!$C$4:$C$400,$A11,Transações!$H$4:$H$400,H$5,Transações!$I$4:$I$400,$B$3) -> 0 | I11: =SUMIFS(Transações!$F$4:$F$400,Transações!$D$4:$D$400,"Despesa",Transações!$C$4:$C$400,$A11,Transações!$H$4:$H$400,I$5,Transações!$I$4:$I$400,$B$3) -> 0 | ... M11: =SUMIFS(Transações!$F$4:$F$400,Transações!$D$4:$D$400,"Despesa",Transações!$C$4:$C$400,$A11,Transações!$H$4:$H$400,M$5,Transações!$I$4:$I$400,$B$3) -> 0 | N11: =SUM(B11:M11) -> 0
A12: Educação | B12: =SUMIFS(Transações!$F$4:$F$400,Transações!$D$4:$D$400,"Despesa",Transações!$C$4:$C$400,$A12,Transações!$H$4:$H$400,B$5,Transações!$I$4:$I$400,$B$3) -> 0 | C12: =SUMIFS(Transações!$F$4:$F$400,Transações!$D$4:$D$400,"Despesa",Transações!$C$4:$C$400,$A12,Transações!$H$4:$H$400,C$5,Transações!$I$4:$I$400,$B$3) -> 0 | D12: =SUMIFS(Transações!$F$4:$F$400,Transações!$D$4:$D$400,"Despesa",Transações!$C$4:$C$400,$A12,Transações!$H$4:$H$400,D$5,Transações!$I$4:$I$400,$B$3) -> 0 | E12: =SUMIFS(Transações!$F$4:$F$400,Transações!$D$4:$D$400,"Despesa",Transações!$C$4:$C$400,$A12,Transações!$H$4:$H$400,E$5,Transações!$I$4:$I$400,$B$3) -> 0 | F12: =SUMIFS(Transações!$F$4:$F$400,Transações!$D$4:$D$400,"Despesa",Transações!$C$4:$C$400,$A12,Transações!$H$4:$H$400,F$5,Transações!$I$4:$I$400,$B$3) -> 0 | G12: =SUMIFS(Transações!$F$4:$F$400,Transações!$D$4:$D$400,"Despesa",Transações!$C$4:$C$400,$A12,Transações!$H$4:$H$400,G$5,Transações!$I$4:$I$400,$B$3) -> 0 | H12: =SUMIFS(Transações!$F$4:$F$400,Transações!$D$4:$D$400,"Despesa",Transações!$C$4:$C$400,$A12,Transações!$H$4:$H$400,H$5,Transações!$I$4:$I$400,$B$3) -> 0 | I12: =SUMIFS(Transações!$F$4:$F$400,Transações!$D$4:$D$400,"Despesa",Transações!$C$4:$C$400,$A12,Transações!$H$4:$H$400,I$5,Transações!$I$4:$I$400,$B$3) -> 0 | ... M12: =SUMIFS(Transações!$F$4:$F$400,Transações!$D$4:$D$400,"Despesa",Transações!$C$4:$C$400,$A12,Transações!$H$4:$H$400,M$5,Transações!$I$4:$I$400,$B$3) -> 0 | N12: =SUM(B12:M12) -> 0
A13: Lazer/Assinaturas | B13: =SUMIFS(Transações!$F$4:$F$400,Transações!$D$4:$D$400,"Despesa",Transações!$C$4:$C$400,$A13,Transações!$H$4:$H$400,B$5,Transações!$I$4:$I$400,$B$3) -> 0 | C13: =SUMIFS(Transações!$F$4:$F$400,Transações!$D$4:$D$400,"Despesa",Transações!$C$4:$C$400,$A13,Transações!$H$4:$H$400,C$5,Transações!$I$4:$I$400,$B$3) -> 0 | D13: =SUMIFS(Transações!$F$4:$F$400,Transações!$D$4:$D$400,"Despesa",Transações!$C$4:$C$400,$A13,Transações!$H$4:$H$400,D$5,Transações!$I$4:$I$400,$B$3) -> 0 | E13: =SUMIFS(Transações!$F$4:$F$400,Transações!$D$4:$D$400,"Despesa",Transações!$C$4:$C$400,$A13,Transações!$H$4:$H$400,E$5,Transações!$I$4:$I$400,$B$3) -> 0 | F13: =SUMIFS(Transações!$F$4:$F$400,Transações!$D$4:$D$400,"Despesa",Transações!$C$4:$C$400,$A13,Transações!$H$4:$H$400,F$5,Transações!$I$4:$I$400,$B$3) -> 0 | G13: =SUMIFS(Transações!$F$4:$F$400,Transações!$D$4:$D$400,"Despesa",Transações!$C$4:$C$400,$A13,Transações!$H$4:$H$400,G$5,Transações!$I$4:$I$400,$B$3) -> 0 | H13: =SUMIFS(Transações!$F$4:$F$400,Transações!$D$4:$D$400,"Despesa",Transações!$C$4:$C$400,$A13,Transações!$H$4:$H$400,H$5,Transações!$I$4:$I$400,$B$3) -> 0 | I13: =SUMIFS(Transações!$F$4:$F$400,Transações!$D$4:$D$400,"Despesa",Transações!$C$4:$C$400,$A13,Transações!$H$4:$H$400,I$5,Transações!$I$4:$I$400,$B$3) -> 0 | ... M13: =SUMIFS(Transações!$F$4:$F$400,Transações!$D$4:$D$400,"Despesa",Transações!$C$4:$C$400,$A13,Transações!$H$4:$H$400,M$5,Transações!$I$4:$I$400,$B$3) -> 0 | N13: =SUM(B13:M13) -> 0
A14: Vestuário | B14: =SUMIFS(Transações!$F$4:$F$400,Transações!$D$4:$D$400,"Despesa",Transações!$C$4:$C$400,$A14,Transações!$H$4:$H$400,B$5,Transações!$I$4:$I$400,$B$3) -> 0 | C14: =SUMIFS(Transações!$F$4:$F$400,Transações!$D$4:$D$400,"Despesa",Transações!$C$4:$C$400,$A14,Transações!$H$4:$H$400,C$5,Transações!$I$4:$I$400,$B$3) -> 0 | D14: =SUMIFS(Transações!$F$4:$F$400,Transações!$D$4:$D$400,"Despesa",Transações!$C$4:$C$400,$A14,Transações!$H$4:$H$400,D$5,Transações!$I$4:$I$400,$B$3) -> 0 | E14: =SUMIFS(Transações!$F$4:$F$400,Transações!$D$4:$D$400,"Despesa",Transações!$C$4:$C$400,$A14,Transações!$H$4:$H$400,E$5,Transações!$I$4:$I$400,$B$3) -> 0 | F14: =SUMIFS(Transações!$F$4:$F$400,Transações!$D$4:$D$400,"Despesa",Transações!$C$4:$C$400,$A14,Transações!$H$4:$H$400,F$5,Transações!$I$4:$I$400,$B$3) -> 0 | G14: =SUMIFS(Transações!$F$4:$F$400,Transações!$D$4:$D$400,"Despesa",Transações!$C$4:$C$400,$A14,Transações!$H$4:$H$400,G$5,Transações!$I$4:$I$400,$B$3) -> 0 | H14: =SUMIFS(Transações!$F$4:$F$400,Transações!$D$4:$D$400,"Despesa",Transações!$C$4:$C$400,$A14,Transações!$H$4:$H$400,H$5,Transações!$I$4:$I$400,$B$3) -> 0 | I14: =SUMIFS(Transações!$F$4:$F$400,Transações!$D$4:$D$400,"Despesa",Transações!$C$4:$C$400,$A14,Transações!$H$4:$H$400,I$5,Transações!$I$4:$I$400,$B$3) -> 0 | ... M14: =SUMIFS(Transações!$F$4:$F$400,Transações!$D$4:$D$400,"Despesa",Transações!$C$4:$C$400,$A14,Transações!$H$4:$H$400,M$5,Transações!$I$4:$I$400,$B$3) -> 0 | N14: =SUM(B14:M14) -> 0
A15: Cuidados Pessoais | B15: =SUMIFS(Transações!$F$4:$F$400,Transações!$D$4:$D$400,"Despesa",Transações!$C$4:$C$400,$A15,Transações!$H$4:$H$400,B$5,Transações!$I$4:$I$400,$B$3) -> 0 | C15: =SUMIFS(Transações!$F$4:$F$400,Transações!$D$4:$D$400,"Despesa",Transações!$C$4:$C$400,$A15,Transações!$H$4:$H$400,C$5,Transações!$I$4:$I$400,$B$3) -> 0 | D15: =SUMIFS(Transações!$F$4:$F$400,Transações!$D$4:$D$400,"Despesa",Transações!$C$4:$C$400,$A15,Transações!$H$4:$H$400,D$5,Transações!$I$4:$I$400,$B$3) -> 0 | E15: =SUMIFS(Transações!$F$4:$F$400,Transações!$D$4:$D$400,"Despesa",Transações!$C$4:$C$400,$A15,Transações!$H$4:$H$400,E$5,Transações!$I$4:$I$400,$B$3) -> 0 | F15: =SUMIFS(Transações!$F$4:$F$400,Transações!$D$4:$D$400,"Despesa",Transações!$C$4:$C$400,$A15,Transações!$H$4:$H$400,F$5,Transações!$I$4:$I$400,$B$3) -> 0 | G15: =SUMIFS(Transações!$F$4:$F$400,Transações!$D$4:$D$400,"Despesa",Transações!$C$4:$C$400,$A15,Transações!$H$4:$H$400,G$5,Transações!$I$4:$I$400,$B$3) -> 0 | H15: =SUMIFS(Transações!$F$4:$F$400,Transações!$D$4:$D$400,"Despesa",Transações!$C$4:$C$400,$A15,Transações!$H$4:$H$400,H$5,Transações!$I$4:$I$400,$B$3) -> 0 | I15: =SUMIFS(Transações!$F$4:$F$400,Transações!$D$4:$D$400,"Despesa",Transações!$C$4:$C$400,$A15,Transações!$H$4:$H$400,I$5,Transações!$I$4:$I$400,$B$3) -> 0 | ... M15: =SUMIFS(Transações!$F$4:$F$400,Transações!$D$4:$D$400,"Despesa",Transações!$C$4:$C$400,$A15,Transações!$H$4:$H$400,M$5,Transações!$I$4:$I$400,$B$3) -> 0 | N15: =SUM(B15:M15) -> 0
A16: Cartão de Crédito | B16: =SUMIFS(Transações!$F$4:$F$400,Transações!$D$4:$D$400,"Despesa",Transações!$C$4:$C$400,$A16,Transações!$H$4:$H$400,B$5,Transações!$I$4:$I$400,$B$3) -> 0 | C16: =SUMIFS(Transações!$F$4:$F$400,Transações!$D$4:$D$400,"Despesa",Transações!$C$4:$C$400,$A16,Transações!$H$4:$H$400,C$5,Transações!$I$4:$I$400,$B$3) -> 0 | D16: =SUMIFS(Transações!$F$4:$F$400,Transações!$D$4:$D$400,"Despesa",Transações!$C$4:$C$400,$A16,Transações!$H$4:$H$400,D$5,Transações!$I$4:$I$400,$B$3) -> 0 | E16: =SUMIFS(Transações!$F$4:$F$400,Transações!$D$4:$D$400,"Despesa",Transações!$C$4:$C$400,$A16,Transações!$H$4:$H$400,E$5,Transações!$I$4:$I$400,$B$3) -> 0 | F16: =SUMIFS(Transações!$F$4:$F$400,Transações!$D$4:$D$400,"Despesa",Transações!$C$4:$C$400,$A16,Transações!$H$4:$H$400,F$5,Transações!$I$4:$I$400,$B$3) -> 0 | G16: =SUMIFS(Transações!$F$4:$F$400,Transações!$D$4:$D$400,"Despesa",Transações!$C$4:$C$400,$A16,Transações!$H$4:$H$400,G$5,Transações!$I$4:$I$400,$B$3) -> 0 | H16: =SUMIFS(Transações!$F$4:$F$400,Transações!$D$4:$D$400,"Despesa",Transações!$C$4:$C$400,$A16,Transações!$H$4:$H$400,H$5,Transações!$I$4:$I$400,$B$3) -> 0 | I16: =SUMIFS(Transações!$F$4:$F$400,Transações!$D$4:$D$400,"Despesa",Transações!$C$4:$C$400,$A16,Transações!$H$4:$H$400,I$5,Transações!$I$4:$I$400,$B$3) -> 0 | ... M16: =SUMIFS(Transações!$F$4:$F$400,Transações!$D$4:$D$400,"Despesa",Transações!$C$4:$C$400,$A16,Transações!$H$4:$H$400,M$5,Transações!$I$4:$I$400,$B$3) -> 0 | N16: =SUM(B16:M16) -> 0
A17: Dívidas/Empréstimos | B17: =SUMIFS(Transações!$F$4:$F$400,Transações!$D$4:$D$400,"Despesa",Transações!$C$4:$C$400,$A17,Transações!$H$4:$H$400,B$5,Transações!$I$4:$I$400,$B$3) -> 0 | C17: =SUMIFS(Transações!$F$4:$F$400,Transações!$D$4:$D$400,"Despesa",Transações!$C$4:$C$400,$A17,Transações!$H$4:$H$400,C$5,Transações!$I$4:$I$400,$B$3) -> 0 | D17: =SUMIFS(Transações!$F$4:$F$400,Transações!$D$4:$D$400,"Despesa",Transações!$C$4:$C$400,$A17,Transações!$H$4:$H$400,D$5,Transações!$I$4:$I$400,$B$3) -> 0 | E17: =SUMIFS(Transações!$F$4:$F$400,Transações!$D$4:$D$400,"Despesa",Transações!$C$4:$C$400,$A17,Transações!$H$4:$H$400,E$5,Transações!$I$4:$I$400,$B$3) -> 0 | F17: =SUMIFS(Transações!$F$4:$F$400,Transações!$D$4:$D$400,"Despesa",Transações!$C$4:$C$400,$A17,Transações!$H$4:$H$400,F$5,Transações!$I$4:$I$400,$B$3) -> 0 | G17: =SUMIFS(Transações!$F$4:$F$400,Transações!$D$4:$D$400,"Despesa",Transações!$C$4:$C$400,$A17,Transações!$H$4:$H$400,G$5,Transações!$I$4:$I$400,$B$3) -> 0 | H17: =SUMIFS(Transações!$F$4:$F$400,Transações!$D$4:$D$400,"Despesa",Transações!$C$4:$C$400,$A17,Transações!$H$4:$H$400,H$5,Transações!$I$4:$I$400,$B$3) -> 0 | I17: =SUMIFS(Transações!$F$4:$F$400,Transações!$D$4:$D$400,"Despesa",Transações!$C$4:$C$400,$A17,Transações!$H$4:$H$400,I$5,Transações!$I$4:$I$400,$B$3) -> 0 | ... M17: =SUMIFS(Transações!$F$4:$F$400,Transações!$D$4:$D$400,"Despesa",Transações!$C$4:$C$400,$A17,Transações!$H$4:$H$400,M$5,Transações!$I$4:$I$400,$B$3) -> 0 | N17: =SUM(B17:M17) -> 0
A18: Impostos/Taxas | B18: =SUMIFS(Transações!$F$4:$F$400,Transações!$D$4:$D$400,"Despesa",Transações!$C$4:$C$400,$A18,Transações!$H$4:$H$400,B$5,Transações!$I$4:$I$400,$B$3) -> 0 | C18: =SUMIFS(Transações!$F$4:$F$400,Transações!$D$4:$D$400,"Despesa",Transações!$C$4:$C$400,$A18,Transações!$H$4:$H$400,C$5,Transações!$I$4:$I$400,$B$3) -> 0 | D18: =SUMIFS(Transações!$F$4:$F$400,Transações!$D$4:$D$400,"Despesa",Transações!$C$4:$C$400,$A18,Transações!$H$4:$H$400,D$5,Transações!$I$4:$I$400,$B$3) -> 0 | E18: =SUMIFS(Transações!$F$4:$F$400,Transações!$D$4:$D$400,"Despesa",Transações!$C$4:$C$400,$A18,Transações!$H$4:$H$400,E$5,Transações!$I$4:$I$400,$B$3) -> 0 | F18: =SUMIFS(Transações!$F$4:$F$400,Transações!$D$4:$D$400,"Despesa",Transações!$C$4:$C$400,$A18,Transações!$H$4:$H$400,F$5,Transações!$I$4:$I$400,$B$3) -> 0 | G18: =SUMIFS(Transações!$F$4:$F$400,Transações!$D$4:$D$400,"Despesa",Transações!$C$4:$C$400,$A18,Transações!$H$4:$H$400,G$5,Transações!$I$4:$I$400,$B$3) -> 0 | H18: =SUMIFS(Transações!$F$4:$F$400,Transações!$D$4:$D$400,"Despesa",Transações!$C$4:$C$400,$A18,Transações!$H$4:$H$400,H$5,Transações!$I$4:$I$400,$B$3) -> 0 | I18: =SUMIFS(Transações!$F$4:$F$400,Transações!$D$4:$D$400,"Despesa",Transações!$C$4:$C$400,$A18,Transações!$H$4:$H$400,I$5,Transações!$I$4:$I$400,$B$3) -> 0 | ... M18: =SUMIFS(Transações!$F$4:$F$400,Transações!$D$4:$D$400,"Despesa",Transações!$C$4:$C$400,$A18,Transações!$H$4:$H$400,M$5,Transações!$I$4:$I$400,$B$3) -> 0 | N18: =SUM(B18:M18) -> 0
... A22: Outras Despesas | B22: =SUMIFS(Transações!$F$4:$F$400,Transações!$D$4:$D$400,"Despesa",Transações!$C$4:$C$400,$A22,Transações!$H$4:$H$400,B$5,Transações!$I$4:$I$400,$B$3) -> 0 | C22: =SUMIFS(Transações!$F$4:$F$400,Transações!$D$4:$D$400,"Despesa",Transações!$C$4:$C$400,$A22,Transações!$H$4:$H$400,C$5,Transações!$I$4:$I$400,$B$3) -> 0 | D22: =SUMIFS(Transações!$F$4:$F$400,Transações!$D$4:$D$400,"Despesa",Transações!$C$4:$C$400,$A22,Transações!$H$4:$H$400,D$5,Transações!$I$4:$I$400,$B$3) -> 0 | E22: =SUMIFS(Transações!$F$4:$F$400,Transações!$D$4:$D$400,"Despesa",Transações!$C$4:$C$400,$A22,Transações!$H$4:$H$400,E$5,Transações!$I$4:$I$400,$B$3) -> 0 | F22: =SUMIFS(Transações!$F$4:$F$400,Transações!$D$4:$D$400,"Despesa",Transações!$C$4:$C$400,$A22,Transações!$H$4:$H$400,F$5,Transações!$I$4:$I$400,$B$3) -> 0 | G22: =SUMIFS(Transações!$F$4:$F$400,Transações!$D$4:$D$400,"Despesa",Transações!$C$4:$C$400,$A22,Transações!$H$4:$H$400,G$5,Transações!$I$4:$I$400,$B$3) -> 0 | H22: =SUMIFS(Transações!$F$4:$F$400,Transações!$D$4:$D$400,"Despesa",Transações!$C$4:$C$400,$A22,Transações!$H$4:$H$400,H$5,Transações!$I$4:$I$400,$B$3) -> 0 | I22: =SUMIFS(Transações!$F$4:$F$400,Transações!$D$4:$D$400,"Despesa",Transações!$C$4:$C$400,$A22,Transações!$H$4:$H$400,I$5,Transações!$I$4:$I$400,$B$3) -> 0 | ... M22: =SUMIFS(Transações!$F$4:$F$400,Transações!$D$4:$D$400,"Despesa",Transações!$C$4:$C$400,$A22,Transações!$H$4:$H$400,M$5,Transações!$I$4:$I$400,$B$3) -> 0 | N22: =SUM(B22:M22) -> 0
A23: Despesas Totais | B23: =SUM(B7:B22) -> 2870.3 | C23: =SUM(C7:C22) -> 0 | D23: =SUM(D7:D22) -> 0 | E23: =SUM(E7:E22) -> 0 | F23: =SUM(F7:F22) -> 0 | G23: =SUM(G7:G22) -> 0 | H23: =SUM(H7:H22) -> 0 | I23: =SUM(I7:I22) -> 0 | ... M23: =SUM(M7:M22) -> 0 | N23: =SUM(B23:M23) -> 2870.3
A24: Saldo do Mês | B24: =B6-B23 -> 3629.7 | C24: =C6-C23 -> 0 | D24: =D6-D23 -> 0 | E24: =E6-E23 -> 0 | F24: =F6-F23 -> 0 | G24: =G6-G23 -> 0 | H24: =H6-H23 -> 0 | I24: =I6-I23 -> 0 | ... M24: =M6-M23 -> 0 | N24: =SUM(B24:M24) -> 3629.7
A25: Saldo Acumulado | B25: =B24 -> 3629.7 | C25: =B25+C24 -> 3629.7 | D25: =C25+D24 -> 3629.7 | E25: =D25+E24 -> 3629.7 | F25: =E25+F24 -> 3629.7 | G25: =F25+G24 -> 3629.7 | H25: =G25+H24 -> 3629.7 | I25: =H25+I24 -> 3629.7 | J25: =I25+J24 -> 3629.7 | ... M25: =L25+M24 -> 3629.7 | N25: =M25 -> 3629.7

Sheet Metas
A1: METAS FINANCEIRAS - Reserva de Emergência, Viagem, etc.
A2: Legenda: preencha Nome da Meta, Valor Objetivo, Valor Já Guardado e Prazo (fundo amarelo). Os demais campos são calculados automaticamente.
A4: Nome da Meta | B4: Valor Objetivo | C4: Valor Já Guardado | D4: Prazo | E4: Meses Restantes | F4: Valor Mensal Necessário | G4: % Concluído
A5: Reserva de Emergência | B5: 15000 | C5: 4000 | D5: 46387 | E5: =IF(D5="","",MAX(DATEDIF(TODAY(),D5,"m"),0)) -> 5 | F5: =IFERROR(IF(E5=0,B5-C5,(B5-C5)/E5),"-") -> 2200 | G5: =IFERROR(C5/B5,"-") -> 0.26666667
E6: =IF(D6="","",MAX(DATEDIF(TODAY(),D6,"m"),0)) | F6: =IFERROR(IF(E6=0,B6-C6,(B6-C6)/E6),"-") -> - | G6: =IFERROR(C6/B6,"-") -> -
E7: =IF(D7="","",MAX(DATEDIF(TODAY(),D7,"m"),0)) | F7: =IFERROR(IF(E7=0,B7-C7,(B7-C7)/E7),"-") -> - | G7: =IFERROR(C7/B7,"-") -> -
E8: =IF(D8="","",MAX(DATEDIF(TODAY(),D8,"m"),0)) | F8: =IFERROR(IF(E8=0,B8-C8,(B8-C8)/E8),"-") -> - | G8: =IFERROR(C8/B8,"-") -> -
E9: =IF(D9="","",MAX(DATEDIF(TODAY(),D9,"m"),0)) | F9: =IFERROR(IF(E9=0,B9-C9,(B9-C9)/E9),"-") -> - | G9: =IFERROR(C9/B9,"-") -> -
E10: =IF(D10="","",MAX(DATEDIF(TODAY(),D10,"m"),0)) | F10: =IFERROR(IF(E10=0,B10-C10,(B10-C10)/E10),"-") -> - | G10: =IFERROR(C10/B10,"-") -> -
E11: =IF(D11="","",MAX(DATEDIF(TODAY(),D11,"m"),0)) | F11: =IFERROR(IF(E11=0,B11-C11,(B11-C11)/E11),"-") -> - | G11: =IFERROR(C11/B11,"-") -> -
E12: =IF(D12="","",MAX(DATEDIF(TODAY(),D12,"m"),0)) | F12: =IFERROR(IF(E12=0,B12-C12,(B12-C12)/E12),"-") -> - | G12: =IFERROR(C12/B12,"-") -> -
E13: =IF(D13="","",MAX(DATEDIF(TODAY(),D13,"m"),0)) | F13: =IFERROR(IF(E13=0,B13-C13,(B13-C13)/E13),"-") -> - | G13: =IFERROR(C13/B13,"-") -> -
E14: =IF(D14="","",MAX(DATEDIF(TODAY(),D14,"m"),0)) | F14: =IFERROR(IF(E14=0,B14-C14,(B14-C14)/E14),"-") -> - | G14: =IFERROR(C14/B14,"-") -> -
E15: =IF(D15="","",MAX(DATEDIF(TODAY(),D15,"m"),0)) | F15: =IFERROR(IF(E15=0,B15-C15,(B15-C15)/E15),"-") -> - | G15: =IFERROR(C15/B15,"-") -> -
E16: =IF(D16="","",MAX(DATEDIF(TODAY(),D16,"m"),0)) | F16: =IFERROR(IF(E16=0,B16-C16,(B16-C16)/E16),"-") -> - | G16: =IFERROR(C16/B16,"-") -> -
E17: =IF(D17="","",MAX(DATEDIF(TODAY(),D17,"m"),0)) | F17: =IFERROR(IF(E17=0,B17-C17,(B17-C17)/E17),"-") -> - | G17: =IFERROR(C17/B17,"-") -> -
... E24: =IF(D24="","",MAX(DATEDIF(TODAY(),D24,"m"),0)) | F24: =IFERROR(IF(E24=0,B24-C24,(B24-C24)/E24),"-") -> - | G24: =IFERROR(C24/B24,"-") -> -

Sheet Cartão de Crédito
A1: CARTÃO DE CRÉDITO - Controle de Compras e Parcelas
A2: Legenda: preencha as colunas A a G (fundo amarelo = campo de entrada). Valor da Parcela e Mês Final são calculados automaticamente.
A4: Cartão | B4: Descrição da Compra | C4: Categoria | D4: Data da Compra | E4: Valor Total | F4: Parcelas | G4: Valor da Parcela | H4: Mês da 1ª Fatura | I4: Status
A5: Cartão Principal | B5: Compra de eletrodoméstico | C5: Outras Despesas | D5: 46034 | E5: 1200 | F5: 6 | G5: =IFERROR(E5/F5,"-") -> 200 | H5: =IF(D5="","",INDEX(Lista_Meses,MONTH(D5))) -> Janeiro | I5: Pendente
G6: =IFERROR(E6/F6,"-") -> - | H6: =IF(D6="","",INDEX(Lista_Meses,MONTH(D6)))
G7: =IFERROR(E7/F7,"-") -> - | H7: =IF(D7="","",INDEX(Lista_Meses,MONTH(D7)))
G8: =IFERROR(E8/F8,"-") -> - | H8: =IF(D8="","",INDEX(Lista_Meses,MONTH(D8)))
G9: =IFERROR(E9/F9,"-") -> - | H9: =IF(D9="","",INDEX(Lista_Meses,MONTH(D9)))
G10: =IFERROR(E10/F10,"-") -> - | H10: =IF(D10="","",INDEX(Lista_Meses,MONTH(D10)))
G11: =IFERROR(E11/F11,"-") -> - | H11: =IF(D11="","",INDEX(Lista_Meses,MONTH(D11)))
G12: =IFERROR(E12/F12,"-") -> - | H12: =IF(D12="","",INDEX(Lista_Meses,MONTH(D12)))
G13: =IFERROR(E13/F13,"-") -> - | H13: =IF(D13="","",INDEX(Lista_Meses,MONTH(D13)))
G14: =IFERROR(E14/F14,"-") -> - | H14: =IF(D14="","",INDEX(Lista_Meses,MONTH(D14)))
G15: =IFERROR(E15/F15,"-") -> - | H15: =IF(D15="","",INDEX(Lista_Meses,MONTH(D15)))
G16: =IFERROR(E16/F16,"-") -> - | H16: =IF(D16="","",INDEX(Lista_Meses,MONTH(D16)))
G17: =IFERROR(E17/F17,"-") -> - | H17: =IF(D17="","",INDEX(Lista_Meses,MONTH(D17)))
... G154: =IFERROR(E154/F154,"-") -> - | H154: =IF(D154="","",INDEX(Lista_Meses,MONTH(D154)))
A155: Total | E155: =SUM(E5:E154) -> 1200

Sheet Listas
A1: Meses | B1: Categorias Receita | C1: Categorias Despesa | D1: Tipo | E1: Forma Pagamento | F1: Status | G1: Todas Categorias
A2: Janeiro | B2: Salário | C2: Moradia (aluguel/condomínio) | D2: Receita | E2: Dinheiro | F2: Pago | G2: Salário
A3: Fevereiro | B3: Freelance/Extra | C3: Contas (água/luz/gás/internet) | D3: Despesa | E3: Débito | F3: Pendente | G3: Freelance/Extra
A4: Março | B4: Rendimentos/Investimentos | C4: Alimentação/Mercado | E4: Crédito | F4: Agendado | G4: Rendimentos/Investimentos
A5: Abril | B5: Aluguel Recebido | C5: Transporte/Combustível | E5: Pix | G5: Aluguel Recebido
A6: Maio | B6: Reembolso | C6: Saúde/Plano de Saúde | E6: Transferência | G6: Reembolso
A7: Junho | B7: Décimo Terceiro/Férias | C7: Educação | E7: Boleto | G7: Décimo Terceiro/Férias
A8: Julho | B8: Outras Receitas | C8: Lazer/Assinaturas | G8: Outras Receitas
A9: Agosto | C9: Vestuário | G9: Moradia (aluguel/condomínio)
A10: Setembro | C10: Cuidados Pessoais | G10: Contas (água/luz/gás/internet)
A11: Outubro | C11: Cartão de Crédito | G11: Alimentação/Mercado
A12: Novembro | C12: Dívidas/Empréstimos | G12: Transporte/Combustível
A13: Dezembro | C13: Impostos/Taxas | G13: Saúde/Plano de Saúde
C14: Doações | G14: Educação
C15: Pets | G15: Lazer/Assinaturas
C16: Investimentos/Poupança | G16: Vestuário
C17: Outras Despesas | G17: Cuidados Pessoais
G18: Cartão de Crédito
G19: Dívidas/Empréstimos
G20: Impostos/Taxas
G21: Doações
G22: Pets
G23: Investimentos/Poupança
G24: Outras Despesas
